gu/cli.py
gu/config.py
gu/version.py
gu/sender/__init__.py
gu/sender/default.py
gu/sender/stdout.py
gu/sender/telegram.py
gu_cli-1.1.3.data/scripts/gu
gu_cli-1.1.3.dist-info/LICENSE
gu_cli-1.1.3.dist-info/METADATA
gu_cli-1.1.3.dist-info/WHEEL
gu_cli-1.1.3.dist-info/top_level.txt
gu_cli-1.1.3.dist-info/RECORD
