Metadata-Version: 2.1
Name: gu-cli
Version: 1.1.3
Summary: A simple CLI that gives you messages or notifications.
Home-page: https://github.com/outloudvi/gu
Author: Outvi V
Author-email: git+oss@outv.im
License: MIT
Platform: UNKNOWN
Classifier: Topic :: Communications
Classifier: Development Status :: 2 - Pre-Alpha
Classifier: Environment :: Console
Classifier: License :: OSI Approved :: MIT License
Classifier: Programming Language :: Python
Classifier: Programming Language :: Python :: 3
Classifier: Programming Language :: Python :: 3.2
Classifier: Programming Language :: Python :: 3.3
Classifier: Programming Language :: Python :: 3.4
Classifier: Programming Language :: Python :: 3.5
Classifier: Programming Language :: Python :: 3.6
Classifier: Programming Language :: Python :: 3.7
Classifier: Programming Language :: Python :: 3.8
Requires-Dist: PyYAML (>5.1)
Requires-Dist: requests
